wcpan/model/__init__.py
wcpan/model/fields.py
wcpan/model/models.py
wcpan.model-1.0.0.dev2.dist-info/DESCRIPTION.rst
wcpan.model-1.0.0.dev2.dist-info/METADATA
wcpan.model-1.0.0.dev2.dist-info/RECORD
wcpan.model-1.0.0.dev2.dist-info/WHEEL
wcpan.model-1.0.0.dev2.dist-info/metadata.json
wcpan.model-1.0.0.dev2.dist-info/top_level.txt
