Metadata-Version: 2.0
Name: wcpan.model
Version: 1.0.0.dev2
Summary: Declarative dictionary-based model classes for Python
Home-page: https://github.com/legnaleurc/wcpan.model
Author: Wei-Cheng Pan
Author-email: legnaleurc@gmail.com
License: UNKNOWN
Platform: UNKNOWN
Classifier: Programming Language :: Python :: 3 :: Only
Classifier: Programming Language :: Python :: 3.3
Classifier: Development Status :: 3 - Alpha
Classifier: Intended Audience :: Developers
Classifier: Operating System :: OS Independent
Classifier: Topic :: Software Development :: Libraries :: Python Modules
